temel.py
temel-1.0.3.dist-info/METADATA
temel-1.0.3.dist-info/WHEEL
temel-1.0.3.dist-info/top_level.txt
temel-1.0.3.dist-info/RECORD
