Metadata-Version: 2.1
Name: temel
Version: 1.0.3
Summary: Elements based HTML template renderer
Home-page: https://github.com/jwdeveloper/Temel
Author: JW
Author-email: jacekwoln@gmail.com
License: MIT
Classifier: Programming Language :: Python :: 3
Classifier: License :: OSI Approved :: MIT License
Classifier: Operating System :: OS Independent
Requires-Python: >=3.6
Requires-Dist: beautifulsoup4 >=4.9.0
Requires-Dist: Jinja2 <4.0.0,>=3.1.4
